green_gdk/_green_gdk.cpython-313-x86_64-linux-gnu.so
green_gdk/__init__.py
green_gdk-0.76.2.dist-info/top_level.txt
green_gdk-0.76.2.dist-info/METADATA
green_gdk-0.76.2.dist-info/WHEEL
green_gdk-0.76.2.dist-info/RECORD
