Metadata-Version: 2.4
Name: green_gdk
Version: 0.76.2
Summary: Blockstream Green Development Kit
Author-email: Blockstream <inquiries@blockstream.com>
License-Expression: MIT
Project-URL: repository, https://github.com/blockstream/gdk
Project-URL: documentation, https://gdk.readthedocs.io/en/release_0.76.2
Project-URL: tracker, https://github.com/blockstream/gdk/issues
Keywords: Bitcoin,wallet,library,BIP32,BIP38,BIP39,secp256k1
Classifier: Development Status :: 5 - Production/Stable
Classifier: Intended Audience :: Developers
Classifier: Topic :: Software Development :: Libraries
Classifier: Programming Language :: Python :: 3.5
Classifier: Programming Language :: Python :: 3.6
Classifier: Programming Language :: Python :: 3.7
Classifier: Programming Language :: Python :: 3.9
